cpymake/__init__.py
cpymake/extension.py
cpymake/command/__init__.py
cpymake/command/build_ext.py
docs/conf.py
cpymake-0.2.1.dist-info/LICENSE
cpymake-0.2.1.dist-info/METADATA
cpymake-0.2.1.dist-info/WHEEL
cpymake-0.2.1.dist-info/entry_points.txt
cpymake-0.2.1.dist-info/top_level.txt
cpymake-0.2.1.dist-info/RECORD
