Metadata-Version: 2.1
Name: cpymake
Version: 0.2.1
Summary: Allows building of CMake defined Python Extension modules
Author-email: James Calo <jamesafcalo@gmail.com>
License: GNU GENERAL PUBLIC LICENSE
Project-URL: Repository, https://github.com/SagaraBattousai/cpymake.git
Classifier: Development Status :: 3 - Alpha
Classifier: License :: OSI Approved :: GNU General Public License v3 (GPLv3)
Classifier: Operating System :: OS Independent
Classifier: Framework :: Setuptools Plugin
Classifier: Topic :: System :: Installation/Setup
Requires-Python: >=3.11
License-File: LICENSE
